[
  {
    "id": "EMP-001",
    "name": "Nafisa Mila",
    "designation": "Front End Developer",
    "type": "Employee",
    "department": "IT",
    "bloodGroup": "B+",
    "level": "4",
    "semester": "1",
    "logo": "/logo.png",
    "photo": "/photo1.jpg",
    "signature": "/sign.jpg",
    "company": "Khulna Agricultural University",
    "phone": "+08812345678",
    "address": "Dhaka, Bangladesh",
    "email": "nafisa@example.com",
    "emergencyContact": "+08898765432",
    "expiry": "Dec-2027",
    "qrCode": "/qr.jpg"
  },
  {
    "id": "EMP-002",
    "name": "Rahim Ahmed",
    "designation": "UI Designer",
    "type": "Employee",
    "department": "Design",
    "bloodGroup": "O+",
    "level": "4",
    "semester": "1",
    "logo": "/logo.png",
    "photo": "/photo2.jpg",
    "signature": "/sign.jpg",
    "company": "Khulna Agricultural University",
    "phone": "+08812345678",
    "address": "Dhaka, Bangladesh",
    "email": "rahim@example.com",
    "emergencyContact": "+08898765432",
    "expiry": "Dec-2027",
    "qrCode": "/qr.jpg"
  }
]
